.gitignore
.pylintrc
.style.yapf
LICENSE
MANIFEST.in
README.md
setup.cfg
setup.py
.github/workflows/ci.yml
examples/.gitignore
examples/demo-figure.png
examples/quick-tour.ipynb
expt/__init__.py
expt/colors.py
expt/data.py
expt/data_loader.py
expt/data_loader_test.py
expt/data_test.py
expt/path_util.py
expt/plot.py
expt/plot_test.py
expt/util.py
expt.egg-info/PKG-INFO
expt.egg-info/SOURCES.txt
expt.egg-info/dependency_links.txt
expt.egg-info/not-zip-safe
expt.egg-info/requires.txt
expt.egg-info/top_level.txt
fixtures/.gitignore
fixtures/sample_csv/progress.csv