Metadata-Version: 2.1
Name: expt
Version: 0.4.2
Summary: EXperiment. Plot. Tabulate.
Home-page: https://github.com/wookayin/expt
Author: Jongwook Choi
Author-email: wookayin@gmail.com
License: MIT
Classifier: Development Status :: 3 - Alpha
Classifier: License :: OSI Approved :: MIT License
Classifier: Operating System :: POSIX :: Linux
Classifier: Programming Language :: Python :: 3.6
Classifier: Programming Language :: Python :: 3.7
Classifier: Programming Language :: Python :: 3.8
Classifier: Topic :: Utilities
Classifier: Topic :: Scientific/Engineering
Requires-Python: >=3.6
Provides-Extra: test
License-File: LICENSE
